polly/__init__.py
polly/driftmeasurement.py
polly/etalonanalysis.py
polly/fileselection.py
polly/kpf.py
polly/log.py
polly/misc.py
polly/parsing.py
polly/plotting.py
polly_kpf-0.2.1.dist-info/METADATA
polly_kpf-0.2.1.dist-info/WHEEL
polly_kpf-0.2.1.dist-info/licenses/LICENSE
polly_kpf-0.2.1.dist-info/RECORD
