Metadata-Version: 2.4
Name: polly-kpf
Version: 0.2.1
Summary: Analysis code for KPF etalon data
Project-URL: Repository, https://github.com/pemberj/polly
Author-email: Jake Pember <jake.pember@kuleuven.be>
License: The MIT License (MIT)
License-File: LICENSE
Keywords: KPF,Keck Planet Finder,RV,chromatic drift,data analysis,etalon,high-resolution spectroscopy,radial velocity
Classifier: Development Status :: 4 - Beta
Classifier: Intended Audience :: Developers
Classifier: Intended Audience :: Science/Research
Classifier: License :: OSI Approved :: MIT License
Classifier: Programming Language :: Python
Classifier: Topic :: Scientific/Engineering :: Astronomy
Requires-Python: >=3.10
Requires-Dist: astropy>=6.1.7
Requires-Dist: matplotlib>=3.10.0
Requires-Dist: numpy>=2.2.0
Requires-Dist: pyfonts>=0.0.2
Requires-Dist: scipy>=1.14.1
Requires-Dist: tqdm>=4.67.1
